genotypes.py
genotypes-0.1.1.dist-info/METADATA
genotypes-0.1.1.dist-info/WHEEL
genotypes-0.1.1.dist-info/RECORD
