Metadata-Version: 2.1
Name: Genotypes
Version: 0.1.1
Summary: Cross genotypes of any size!
License: Apache-2.0
Author: GrandMoff100
Author-email: nlarsen23.student@gmail.com
Requires-Python: >=3.8,<4.0
Classifier: License :: OSI Approved :: Apache Software License
Classifier: Programming Language :: Python :: 3
Classifier: Programming Language :: Python :: 3.8
Classifier: Programming Language :: Python :: 3.9
Classifier: Programming Language :: Python :: 3.10
Classifier: Programming Language :: Python :: 3.11
Classifier: Programming Language :: Python :: 3.12
